<?xml version="1.0" encoding="utf-8"?>
<contentList>
	<content contentuid="h7c7a5640g9cc0g45bcg8409gab595be775ec" version="1">Dragon Ogre</content>
	<content contentuid="hf7ea72deg5c14g4ac2g8a68ga282508ae8d1" version="1">A vile and perverse interbreed between the majestic dragon, and the lesser so ogre; these monstrosities are a force of destruction few, if any, can stop.</content>
	<content contentuid="h53bef005g4346g4950gbcf9g39963edb0218" version="1">Dova Beam</content>
	<content contentuid="h3ef3ca55gf349g4ab8g83a1g0ab4da625ac3" version="1">Channel your draconic heritage; fire a beam of light from your maw at your foes.</content>
	<content contentuid="hb2adfb25g0bedg4adagafaeg1782c8eab890" version="1">Embrace the Void</content>
	<content contentuid="h8e99807cgf7d0g4d4bgbb9fgac94dbbf30af" version="1">Darkness Beckons</content>
	<content contentuid="h121c4aa9g3dd4g41dcgb56agfc520a17f9a9" version="1">The swirling black blood within your heart protects you; you are resistant to Radiant damage.</content>
	<content contentuid="h435a6227g8b4fg451fg961dg4fa37b847e74" version="1">Pack Mule</content>
	<content contentuid="h25d5d749g00e3g4212g97a3g15e3e3b97b4c" version="1">Trample the Downtrodden</content>
	<content contentuid="h790d9d20g640ag4ce2g8503gfc11769f39cc" version="1">If a foe is attacked while maimed, apply your Strength modifier to the strike.</content>
	<content contentuid="h09fd5d4bg750fg48c4gbb06gcbf6fee97a54" version="1">Death Sentence</content>
	<content contentuid="h079f2327g42beg43b1g99dcgb00da8573463" version="1">The final hour has arrived. If you critically strike a foe that is maimed, apply an extra dice of damage to your main and offhand weapon attacks.</content>
	<content contentuid="h0059384bg9903g4112g88a8ga199ca04d7eb" version="1">Like the dragons before you, you are prone to hoarding items. Your carrying capacity is increased by a quarter.</content>
	<content contentuid="" version="1"></content>
	<content contentuid="" version="1"></content>
	<content contentuid="" version="1"></content>
	<content contentuid="" version="1"></content>
	<content contentuid="" version="1"></content>
	<content contentuid="" version="1"></content>
	<content contentuid="" version="1"></content>
	<content contentuid="" version="1"></content>
	<content contentuid="" version="1"></content>
	<content contentuid="" version="1"></content>
	<content contentuid="" version="1"></content>
</contentList>
